README.txt
setup.py
sqlitex/__init__.py
sqlitex/api.py
sqlitex/web.py
sqlitex.egg-info/PKG-INFO
sqlitex.egg-info/SOURCES.txt
sqlitex.egg-info/dependency_links.txt
sqlitex.egg-info/entry_points.txt
sqlitex.egg-info/not-zip-safe
sqlitex.egg-info/requires.txt
sqlitex.egg-info/top_level.txt