Metadata-Version: 1.0
Name: sqlitex
Version: 0.0
Summary: sqlite explorer via web
Home-page: http://k0s.org/hg/sqlitex
Author: Jeff Hammel
Author-email: k0scist@gmail.com
License: UNKNOWN
Platform: UNKNOWN
